setup.py
bin/viadict
viadict/__init__.py
viadict/defaults.py
viadict.egg-info/PKG-INFO
viadict.egg-info/SOURCES.txt
viadict.egg-info/dependency_links.txt
viadict.egg-info/not-zip-safe
viadict.egg-info/top_level.txt