Metadata-Version: 1.0
Name: viadict
Version: 0.1.1
Summary: ViaDict is a command-line interface to the OS X Dictionary service.
Home-page: http://github.com/nickbarnwell/viadict
Author: Nicholas Barnwell
Author-email: nb@ul.io
License: MIT
Platform: darwin
